<levels>
	<mission>
		<level name="SD_Playtest2_01" path="SD_Playtest2_01.lvl" type="Infiltration"></level>
		<level name="SD_Playtest2_02" path="SD_Playtest2_02.lvl" type="Infiltration"></level>
		<level name="SD_Playtest2_03" path="SD_Playtest2_03.lvl" type="Infiltration"></level>
		<level name="SD_Playtest2_04" path="SD_Playtest2_04.lvl" type="Infiltration"></level>
		<level name="SD_Playtest2_05" path="SD_Playtest2_05.lvl" type="Infiltration"></level>
		<level name="SD_Playtest2_06" path="SD_Playtest2_06.lvl" type="Infiltration"></level>
		<level name="SD_Playtest2_07" path="SD_Playtest2_07.lvl" type="Infiltration"></level>
		<level name="SD_Playtest2_08" path="SD_Playtest2_08.lvl" type="Infiltration"></level>
		<level name="Thief_Guard_Easy" path="Thief_Guard_Easy.lvl" type="Infiltration"></level>
	</mission>
</levels>